MANIFEST.in
README.rst
readme.rst
requirements.txt
setup.py
taskwarrior_timebook_hook/__init__.py
taskwarrior_timebook_hook.egg-info/PKG-INFO
taskwarrior_timebook_hook.egg-info/SOURCES.txt
taskwarrior_timebook_hook.egg-info/dependency_links.txt
taskwarrior_timebook_hook.egg-info/entry_points.txt
taskwarrior_timebook_hook.egg-info/requires.txt
taskwarrior_timebook_hook.egg-info/top_level.txt