Metadata-Version: 1.1
Name: taskwarrior-timebook-hook
Version: 0.3
Summary: ('Track your tasks as Timebook entries',)
Home-page: https://github.com/coddingtonbear/taskwarrior-timebook-hook
Author: Adam Coddington
Author-email: me@adamcoddington.net
License: UNKNOWN
Platform: UNKNOWN
Classifier: License :: OSI Approved :: MIT License
Classifier: Operating System :: OS Independent
